{
  "navbar": {
    "logo": "Portfolio",
    "links": [
      { "id": "hero", "label": "Головна" },
      { "id": "about", "label": "Про мене" },
      { "id": "results", "label": "Результати" },
      { "id": "methods", "label": "Методична робота" },
      { "id": "contact", "label": "Контакти" }
    ],
    "menuLabel": "Меню"
  },
  "hero": {
    "badge": "Teacher Portfolio",
    "primaryButton": "Дізнатись більше",
    "secondaryButton": "Контакти"
  },
  "about": {
    "title": "Про мене",
    "details": [
      { "label": "Освіта", "icon": "GraduationCap", "field": "education" },
      { "label": "Стаж", "icon": "Briefcase", "field": "experience" },
      { "label": "Рівень мови", "icon": "Globe", "field": "language_level" },
      { "label": "Категорія", "icon": "Award", "field": "category" }
    ],
    "achievementsTitle": "Досягнення"
  },
  "results": {
    "title": "Результати",
    "description": "Досягнення моїх учнів — найкраще підтвердження ефективності навчання.",
    "categories": [
      { "name": "Успішність", "icon": "Users", "color": "bg-blue-50 text-blue-700" },
      { "name": "Олімпіади", "icon": "Trophy", "color": "bg-amber-50 text-amber-700" },
      { "name": "Конкурси", "icon": "BookOpen", "color": "bg-emerald-50 text-emerald-700" },
      { "name": "Проєкти", "icon": "FlaskConical", "color": "bg-purple-50 text-purple-700" }
    ],
    "fallbackCategory": "bg-gray-50 text-gray-600"
  },
  "methods": {
    "title": "Методична робота",
    "readMore": "Читати статтю"
  },
  "contact": {
    "title": "Контакти",
    "emailLabel": "Email",
    "phoneLabel": "Телефон",
    "profileLabel": "Профіль"
  },
  "footer": {
    "logo": "Portfolio",
    "rights": "Всі права захищено"
  }
}
